{
  "descriptionHash": "0CF41903C2EA358113F40225B1A2BB1FF32F5411CF586B28E37AD2450B81D3E495ED8F7653EB6146547CCE33477B293AA03085E7523BEEB15A24072A6FEBB457",
  "descriptionLocation": "../../fixed.json",
  "lockFileVersion": "1.0.0",
  "kiotaVersion": "1.34.0",
  "clientClassName": "N8nOpenApiClient",
  "typeAccessModifier": "Public",
  "clientNamespaceName": "Soenneker.N8n.OpenApiClient",
  "language": "CSharp",
  "usesBackingStore": false,
  "excludeBackwardCompatible": true,
  "includeAdditionalData": true,
  "disableSSLValidation": false,
  "serializers": [
    "Microsoft.Kiota.Serialization.Json.JsonSerializationWriterFactory",
    "Microsoft.Kiota.Serialization.Text.TextSerializationWriterFactory",
    "Microsoft.Kiota.Serialization.Form.FormSerializationWriterFactory",
    "Microsoft.Kiota.Serialization.Multipart.MultipartSerializationWriterFactory"
  ],
  "deserializers": [
    "Microsoft.Kiota.Serialization.Json.JsonParseNodeFactory",
    "Microsoft.Kiota.Serialization.Text.TextParseNodeFactory",
    "Microsoft.Kiota.Serialization.Form.FormParseNodeFactory"
  ],
  "structuredMimeTypes": [
    "application/json",
    "text/plain;q=0.9",
    "application/x-www-form-urlencoded;q=0.2",
    "multipart/form-data;q=0.1"
  ],
  "includePatterns": [],
  "excludePatterns": [],
  "disabledValidationRules": [],
  "allowedExternalOrigins": []
}